[
  {
    "name": "РС€РёРјР±Р°Р№",
    "name_alt": "РС€РёРјР±Р°Р№",
    "label": "ishimbay",
    "type": "Р“РѕСЂРѕРґ",
    "typeShort": "Рі",
    "contentType": "city",
    "id": "0202600100000",
    "okato": "80420000000",
    "oktmo": "80631101001",
    "guid": "b3d2e10f-752d-4b90-b54b-9d6545f38ae0",
    "isDualName": false,
    "isCapital": false,
    "zip": 453201,
    "population": 64041,
    "yearFounded": 1932,
    "yearCityStatus": 1940,
    "name_en": "Ishimbay",
    "namecase": {
      "nominative": "РС€РёРјР±Р°Р№",
      "genitive": "РС€РёРјР±Р°СЏ",
      "dative": "РС€РёРјР±Р°СЋ",
      "accusative": "РС€РёРјР±Р°Р№",
      "ablative": "РС€РёРјР±Р°РµРј",
      "prepositional": "РС€РёРјР±Р°Рµ",
      "locative": "РС€РёРјР±Р°Рµ"
    },
    "coords": { "lat": 53.4545764, "lon": 56.0438751 },
    "timezone": {
      "tzid": "Asia/Yekaterinburg",
      "abbreviation": "YEKT",
      "utcOffset": "UTC+05:00",
      "mskOffset": "MSK+02"
    },
    "region": {
      "name": "Р‘Р°С€РєРѕСЂС‚РѕСЃС‚Р°РЅ",
      "label": "bashkortostan",
      "type": "Р РµСЃРїСѓР±Р»РёРєР°",
      "typeShort": "Р РµСЃРї",
      "contentType": "region",
      "id": "0200000000000",
      "okato": "80000000000",
      "oktmo": "80000000",
      "guid": "6f2cbfd8-692a-4ee4-9b16-067210bde3fc",
      "code": "02",
      "iso_3166-2": "RU-BA",
      "population": 4091423,
      "yearFounded": 1919,
      "area": 142947,
      "fullname": "Р РµСЃРїСѓР±Р»РёРєР° Р‘Р°С€РєРѕСЂС‚РѕСЃС‚Р°РЅ",
      "unofficialName": "Р‘Р°С€РєРёСЂРёСЏ",
      "name_en": "Republic of Bashkortostan",
      "district": "РџСЂРёРІРѕР»Р¶СЃРєРёР№",
      "namecase": {
        "nominative": "Р РµСЃРїСѓР±Р»РёРєР° Р‘Р°С€РєРѕСЂС‚РѕСЃС‚Р°РЅ",
        "genitive": "Р РµСЃРїСѓР±Р»РёРєРё Р‘Р°С€РєРѕСЂС‚РѕСЃС‚Р°РЅ",
        "dative": "Р РµСЃРїСѓР±Р»РёРєРµ Р‘Р°С€РєРѕСЂС‚РѕСЃС‚Р°РЅ",
        "accusative": "Р РµСЃРїСѓР±Р»РёРєСѓ Р‘Р°С€РєРѕСЂС‚РѕСЃС‚Р°РЅ",
        "ablative": "Р РµСЃРїСѓР±Р»РёРєРѕР№ Р‘Р°С€РєРѕСЂС‚РѕСЃС‚Р°РЅ",
        "prepositional": "Р РµСЃРїСѓР±Р»РёРєРµ Р‘Р°С€РєРѕСЂС‚РѕСЃС‚Р°РЅ",
        "locative": "Р РµСЃРїСѓР±Р»РёРєРµ Р‘Р°С€РєРѕСЂС‚РѕСЃС‚Р°РЅ"
      },
      "capital": {
        "name": "РЈС„Р°",
        "label": "ufa",
        "id": "0200000100000",
        "okato": "80401000000",
        "oktmo": "80701000",
        "contentType": "city"
      }
    }
  },
  {
    "name": "РљСѓРјРµСЂС‚Р°Сѓ",
    "name_alt": "РљСѓРјРµСЂС‚Р°Сѓ",
    "label": "kumertau",
    "type": "Р“РѕСЂРѕРґ",
    "typeShort": "Рі",
    "contentType": "city",
    "id": "0200000700000",
    "okato": "80423000000",
    "oktmo": "80723000001",
    "guid": "48e38991-07fd-4aaa-b240-a7280e4a823f",
    "isDualName": false,
    "isCapital": false,
    "zip": 453306,
    "population": 57949,
    "yearFounded": 1947,
    "yearCityStatus": 1953,
    "name_en": "Kumertau",
    "namecase": {
      "nominative": "РљСѓРјРµСЂС‚Р°Сѓ",
      "genitive": "РљСѓРјРµСЂС‚Р°Сѓ",
      "dative": "РљСѓРјРµСЂС‚Р°Сѓ",
      "accusative": "РљСѓРјРµСЂС‚Р°Сѓ",
      "ablative": "РљСѓРјРµСЂС‚Р°Сѓ",
      "prepositional": "РљСѓРјРµСЂС‚Р°Сѓ",
      "locative": "РљСѓРјРµСЂС‚Р°Сѓ"
    },
